MANIFEST.in
PYPI_README.md
README.md
requirements.txt
setup.cfg
setup.py
runloop_api/__init__.py
runloop_api/api.py
runloop_api/net.py
runloop_api.egg-info/PKG-INFO
runloop_api.egg-info/SOURCES.txt
runloop_api.egg-info/dependency_links.txt
runloop_api.egg-info/requires.txt
runloop_api.egg-info/top_level.txt