Metadata-Version: 2.1
Name: runloop-api
Version: 0.0.2
Requires-Dist: requests==2.32.3
